disponibilidade_nfe/nfe.py
disponibilidade_nfe-0.1.0.dist-info/LICENSE
disponibilidade_nfe-0.1.0.dist-info/WHEEL
disponibilidade_nfe-0.1.0.dist-info/METADATA
disponibilidade_nfe-0.1.0.dist-info/RECORD
