Metadata-Version: 2.1
Name: disponibilidade-nfe
Version: 0.1.0
Summary: Web scraping da Disponibilidade dos Webservices da Sefaz através do portal NFe.
Home-page: https://github.com/leogregianin/disponibilidade-nfe
License: MIT
Author: Leonardo Gregianin
Author-email: leogregianin@gmail.com
Requires-Python: >=3.6,<4.0
Classifier: License :: OSI Approved :: MIT License
Classifier: Programming Language :: Python :: 3
Classifier: Programming Language :: Python :: 3.10
Classifier: Programming Language :: Python :: 3.6
Classifier: Programming Language :: Python :: 3.7
Classifier: Programming Language :: Python :: 3.8
Classifier: Programming Language :: Python :: 3.9
Requires-Dist: beautifulsoup4 (>=4.10.0,<5.0.0)
Requires-Dist: requests (>=2.26.0,<3.0.0)
Requires-Dist: requests-mock (>=1.9.3,<2.0.0)
Project-URL: Repository, https://github.com/leogregianin/disponibilidade-nfe
